preprocess_gpak/__init__.py
preprocess_gpak/text_preprocess.py
preprocess_gpak-1.0.2.dist-info/LICENSE
preprocess_gpak-1.0.2.dist-info/METADATA
preprocess_gpak-1.0.2.dist-info/WHEEL
preprocess_gpak-1.0.2.dist-info/top_level.txt
preprocess_gpak-1.0.2.dist-info/RECORD
