Metadata-Version: 2.2
Name: preprocess_gpak
Version: 1.0.2
Summary: A package to preprocess the text data
Author: Pavan Aditya Kumar Gorrela
Author-email: pavanadityakumarg2004@gmail.com
Classifier: Programming Language :: Python :: 3
Classifier: License :: OSI Approved :: MIT License
Classifier: Operating System :: OS Independent
Requires-Python: >=3.7
License-File: LICENSE
Dynamic: author
Dynamic: author-email
Dynamic: classifier
Dynamic: description
Dynamic: description-content-type
Dynamic: requires-python
Dynamic: summary
